README
setup.cfg
setup.py
gtapps_mp/__init__.py
gtapps_mp/gtdiffrsp_mp.py
gtapps_mp/gtexpmap_mp.py
gtapps_mp/gtltcube_mp.py
gtapps_mp/gtsrcmaps_mp.py
gtapps_mp/gttsmap_mp.py
gtapps_mp/utils.py
gtapps_mp.egg-info/PKG-INFO
gtapps_mp.egg-info/SOURCES.txt
gtapps_mp.egg-info/dependency_links.txt
gtapps_mp.egg-info/entry_points.txt
gtapps_mp.egg-info/top_level.txt