Metadata-Version: 1.0
Name: gtapps-mp
Version: 1.4
Summary: Fermi LAT Multicore Scripts
Home-page: https://github.com/fermiPy
Author: Jeremy S. Perkins (fermiPy)
Author-email: jeremy.s.perkins@nasa.gov
License: MIT
Platform: UNKNOWN
